huaweicloudsdkdbss/__init__.py
huaweicloudsdkdbss/v1/__init__.py
huaweicloudsdkdbss/v1/dbss_async_client.py
huaweicloudsdkdbss/v1/dbss_client.py
huaweicloudsdkdbss/v1/model/__init__.py
huaweicloudsdkdbss/v1/model/add_audit_agent_new_request.py
huaweicloudsdkdbss/v1/model/add_audit_agent_new_response.py
huaweicloudsdkdbss/v1/model/add_audit_agent_request.py
huaweicloudsdkdbss/v1/model/add_audit_agent_response.py
huaweicloudsdkdbss/v1/model/add_audit_database_new_request.py
huaweicloudsdkdbss/v1/model/add_audit_database_new_response.py
huaweicloudsdkdbss/v1/model/add_audit_database_request.py
huaweicloudsdkdbss/v1/model/add_audit_database_response.py
huaweicloudsdkdbss/v1/model/add_rds_database_new_request.py
huaweicloudsdkdbss/v1/model/add_rds_database_new_response.py
huaweicloudsdkdbss/v1/model/add_rds_database_request.py
huaweicloudsdkdbss/v1/model/add_rds_database_response.py
huaweicloudsdkdbss/v1/model/add_rds_no_agent_database_request.py
huaweicloudsdkdbss/v1/model/add_rds_no_agent_database_response.py
huaweicloudsdkdbss/v1/model/add_whitelist_request.py
huaweicloudsdkdbss/v1/model/agent_edit_request.py
huaweicloudsdkdbss/v1/model/agent_switch_request.py
huaweicloudsdkdbss/v1/model/alarm_log_request.py
huaweicloudsdkdbss/v1/model/alarm_log_request_time.py
huaweicloudsdkdbss/v1/model/alarm_log_response_alarm_log.py
huaweicloudsdkdbss/v1/model/alarm_log_response_new_alarm_log.py
huaweicloudsdkdbss/v1/model/audit_agent_request.py
huaweicloudsdkdbss/v1/model/audit_agent_respoonse_agents.py
huaweicloudsdkdbss/v1/model/audit_instance_list_bean.py
huaweicloudsdkdbss/v1/model/audit_instance_risk_count.py
huaweicloudsdkdbss/v1/model/audit_scope_request_new.py
huaweicloudsdkdbss/v1/model/audit_scope_switch_request_new.py
huaweicloudsdkdbss/v1/model/audit_sql_request.py
huaweicloudsdkdbss/v1/model/audit_sql_request_time.py
huaweicloudsdkdbss/v1/model/audit_sql_response_sql.py
huaweicloudsdkdbss/v1/model/audit_sql_response_sql_operated_obj_info.py
huaweicloudsdkdbss-3.1.184.dist-info/METADATA
huaweicloudsdkdbss-3.1.184.dist-info/WHEEL
huaweicloudsdkdbss-3.1.184.dist-info/licenses/LICENSE
huaweicloudsdkdbss-3.1.184.dist-info/RECORD
